.gitignore
.travis.yml
CHANGES.rst
LICENSE
MANIFEST.in
README.rst
setup.cfg
setup.py
tox.ini
docs/Makefile
docs/advanced.rst
docs/conf.py
docs/development.rst
docs/documentation_styleguide.rst
docs/index.rst
docs/rst-styleguide.rst
docs/theme_preview.rst
docs/tox-notes.txt
docs/usage.rst
docs/_static/plone_org_5.png
docs/_templates/doormat.html
src/sphinxtheme/__init__.py
src/sphinxtheme.plone.egg-info/PKG-INFO
src/sphinxtheme.plone.egg-info/SOURCES.txt
src/sphinxtheme.plone.egg-info/dependency_links.txt
src/sphinxtheme.plone.egg-info/entry_points.txt
src/sphinxtheme.plone.egg-info/namespace_packages.txt
src/sphinxtheme.plone.egg-info/not-zip-safe
src/sphinxtheme.plone.egg-info/requires.txt
src/sphinxtheme.plone.egg-info/top_level.txt
src/sphinxtheme/plone/__init__.py
src/sphinxtheme/plone/plone_barceloneta/theme.conf
src/sphinxtheme/plone/plone_basic/doormat.html
src/sphinxtheme/plone/plone_basic/footer.html
src/sphinxtheme/plone/plone_basic/header.html
src/sphinxtheme/plone/plone_basic/layout.html
src/sphinxtheme/plone/plone_basic/searchbox.html
src/sphinxtheme/plone/plone_basic/theme.conf
src/sphinxtheme/plone/plone_basic/topbar.html
src/sphinxtheme/plone/plone_basic/version_buttondropdown.html
src/sphinxtheme/plone/plone_basic/version_warning.html
src/sphinxtheme/plone/plone_basic/versions.html
src/sphinxtheme/plone/plone_basic/static/css/admonition.css
src/sphinxtheme/plone/plone_basic/static/css/bootstrap-theme.css
src/sphinxtheme/plone/plone_basic/static/css/bootstrap-theme.css.map
src/sphinxtheme/plone/plone_basic/static/css/bootstrap-theme.min.css
src/sphinxtheme/plone/plone_basic/static/css/bootstrap-theme.min.css.map
src/sphinxtheme/plone/plone_basic/static/css/bootstrap.css
src/sphinxtheme/plone/plone_basic/static/css/bootstrap.css.map
src/sphinxtheme/plone/plone_basic/static/css/bootstrap.min.css
src/sphinxtheme/plone/plone_basic/static/css/bootstrap.min.css.map
src/sphinxtheme/plone/plone_basic/static/css/font-awesome.css
src/sphinxtheme/plone/plone_basic/static/css/font-awesome.min.css
src/sphinxtheme/plone/plone_basic/static/css/plone-fonts.css
src/sphinxtheme/plone/plone_basic/static/css/plone_barceloneta.css
src/sphinxtheme/plone/plone_basic/static/css/plone_basic.css
src/sphinxtheme/plone/plone_basic/static/css/plone_classic.css
src/sphinxtheme/plone/plone_basic/static/css/ploneorg4.css
