Metadata-Version: 1.2
Name: sphinxtheme.plone
Version: 0.5.8
Summary: Collection of Sphinx Themes for Plone Documentations
Home-page: https://github.com/plone/sphinxtheme.plone.git
Author: Alexander Loechel on behalf of Plone Foundation
Author-email: plone-developers@lists.sourceforge.net
Maintainer: Alexander Loechel on behalf of Plone Foundation
Maintainer-email: Alexander.Loechel@lmu.de
License: GPL
Keywords: sphinxtheme sphinx plone themes
Platform: UNKNOWN
Classifier: Framework :: Sphinx
Classifier: Programming Language :: Python :: 2.7
Classifier: Programming Language :: Python :: 3.4
Classifier: Programming Language :: Python :: 3.5
Classifier: Programming Language :: Python :: 3.6
Classifier: Programming Language :: Python :: 3.7
Classifier: Programming Language :: Python :: 3.8
Classifier: Programming Language :: Python :: Implementation :: CPython
Classifier: Programming Language :: Python :: Implementation :: PyPy
Classifier: License :: OSI Approved :: GNU General Public License (GPL)
Classifier: Topic :: Software Development :: Documentation
Classifier: Operating System :: OS Independent
Classifier: Development Status :: 5 - Production/Stable
Classifier: Environment :: Web Environment
Classifier: Intended Audience :: Developers
